AUTHORS.rst
LICENSE.txt
MANIFEST.in
README.rst
requirements.txt
setup.py
docs/model/appendix.tex
docs/model/commands.tex
docs/model/model.tex
docs/source/conf.py
docs/source/fa.rst
docs/source/index.rst
docs/source/mfa.rst
vbmfa/__init__.py
vbmfa/fa.py
vbmfa/mfa.py
vbmfa.egg-info/PKG-INFO
vbmfa.egg-info/SOURCES.txt
vbmfa.egg-info/dependency_links.txt
vbmfa.egg-info/requires.txt
vbmfa.egg-info/top_level.txt