Metadata-Version: 1.1
Name: vbmfa
Version: 0.0.1
Summary: Variational Bayesian Mixture of Factor Analysers
Home-page: https://github.com/cangermueller/vbmfa
Author: Christof Angermueller
Author-email: cangermueller@gmail.com
License: GNU GPLv3+
Keywords: Factor Analysis,PCA,Probabilistic PCA,Dimensionality Reduction,Clustering
Platform: UNKNOWN
Classifier: Development Status :: 4 - Beta
Classifier: Intended Audience :: Developers
Classifier: Intended Audience :: Education
Classifier: Intended Audience :: Science/Research
Classifier: License :: OSI Approved :: GNU General Public License v3 or later (GPLv3+)
Classifier: Operating System :: MacOS
Classifier: Operating System :: POSIX :: Linux
Classifier: Programming Language :: Python
Classifier: Programming Language :: Python :: 2
Classifier: Programming Language :: Python :: 2.7
Classifier: Programming Language :: Python :: 3
Classifier: Programming Language :: Python :: 3.4
Classifier: Topic :: Scientific/Engineering :: Artificial Intelligence
Classifier: Topic :: Scientific/Engineering :: Bio-Informatics
Classifier: Topic :: Scientific/Engineering :: Image Recognition
Classifier: Topic :: Scientific/Engineering :: Information Analysis
